{"201":{"record":[{"type":"total","summary":"2-0","displayValue":"2-0"},{"type":"home","summary":"2-0","displayValue":"2-0"},{"type":"vsconf","summary":"0-0","displayValue":"0-0"}],"linescores":[{"displayValue":"14"},{"displayValue":"7"},{"displayValue":"10"},{"displayValue":"20"}],"statistics":[{"name":"firstDowns","displayValue":"25","value":25.0,"label":"1st Downs"},{"name":"thirdDownEff","displayValue":"6-11","value":0.5454545455,"label":"3rd down efficiency"},{"name":"fourthDownEff","displayValue":"1-2","value":0.5,"label":"4th down efficiency"},{"name":"totalYards","displayValue":"411","value":"-","label":"Total Yards"},{"name":"netPassingYards","displayValue":"303","value":303.0,"label":"Passing"},{"name":"completionAttempts","displayValue":"22/28","value":"-","label":"Comp/Att"},{"name":"yardsPerPass","displayValue":"10.5","value":10.536,"label":"Yards per pass"},{"name":"rushingYards","displayValue":"116","value":116.0,"label":"Rushing"},{"name":"rushingAttempts","displayValue":"45","value":45.0,"label":"Rushing Attempts"},{"name":"yardsPerRushAttempt","displayValue":"2.6","value":2.578,"label":"Yards per rush"},{"name":"totalPenaltiesYards","displayValue":"6-36","value":"-","label":"Penalties"},{"name":"turnovers","displayValue":"2","value":"-","label":"Turnovers"},{"name":"fumblesLost","displayValue":"2","value":2.0,"label":"Fumbles lost"},{"name":"interceptions","displayValue":"0","value":0.0,"label":"Interceptions thrown"},{"name":"possessionTime","displayValue":"20:02","value":1202,"label":"Possession"}],"leaders":[{"name":"passingYards","displayName":"Passing Yards","leaders":[{"displayValue":"19/25, 205 YDS, 5 TD","value":205.0,"athlete":{"id":"188934","uid":"s:20~l:23~a:188934","guid":"24761419-5e55-5d97-07fa-246ea30440eb","lastName":"Bradford","fullName":"Sam Bradford","displayName":"Sam Bradford","shortName":"S. Bradford","links":[{"rel":["playercard","desktop","athlete"],"href":"https://www.espn.com/college-football/player/_/id/188934/sam-bradford","text":"Player Card"}],"jersey":"14 ","position":{"name":"Quarterback","displayName":"Quarterback","abbreviation":"QB"},"status":{"id":"2","name":"Inactive","type":"inactive","abbreviation":"Inactive"}},"mainStat":{"value":"205","label":"YDS"},"summary":"19/25, 5 TD"}]},{"name":"rushingYards","displayName":"Rushing Yards","leaders":[{"displayValue":"15 CAR, 64 YDS","value":64.0,"athlete":{"id":"188948","uid":"s:20~l:23~a:188948","guid":"fb5fb563-a656-9e70-4356-fa74251ff8f1","lastName":"Murray","fullName":"DeMarco Murray","displayName":"DeMarco Murray","shortName":"D. Murray","links":[{"rel":["playercard","desktop","athlete"],"href":"https://www.espn.com/college-football/player/_/id/188948/demarco-murray","text":"Player Card"}],"jersey":"7  ","position":{"name":"Running Back","displayName":"Running Back","abbreviation":"RB"},"status":{"id":"2","name":"Inactive","type":"inactive","abbreviation":"Inactive"}},"mainStat":{"value":"64","label":"YDS"},"summary":"15 CAR"}]},{"name":"receivingYards","displayName":"Receiving Yards","leaders":[{"displayValue":"4 REC, 102 YDS, 3 TD","value":102.0,"athlete":{"id":"174567","uid":"s:20~l:23~a:174567","guid":"e1fddc63-e274-716e-26ba-f8f11bd713cc","lastName":"Kelly","fullName":"Malcolm Kelly","displayName":"Malcolm Kelly","shortName":"M. Kelly","links":[{"rel":["playercard","desktop","athlete"],"href":"https://www.espn.com/college-football/player/_/id/174567/malcolm-kelly","text":"Player Card"}],"jersey":"12 ","position":{"name":"Wide Receiver","displayName":"Wide Receiver","abbreviation":"WR"},"status":{"id":"2","name":"Inactive","type":"inactive","abbreviation":"Inactive"}},"mainStat":{"value":"102","label":"YDS"},"summary":"4 REC, 3 TD"}]},{"name":"sacks","displayName":"Sacks","leaders":[{"displayValue":"1","value":1.0,"athlete":{"id":"145520","uid":"s:20~l:23~a:145520","guid":"96af7e78-79b9-0266-5690-c8c2a4b767ef","lastName":"Dotson","fullName":"Alonzo Dotson","displayName":"Alonzo Dotson","shortName":"A. Dotson","links":[{"rel":["playercard","desktop","athlete"],"href":"https://www.espn.com/college-football/player/_/id/145520/alonzo-dotson","text":"Player Card"}],"jersey":"91 ","position":{"name":"Defensive End","displayName":"Defensive End","abbreviation":"DE"},"status":{"id":"2","name":"Inactive","type":"inactive","abbreviation":"Inactive"}},"mainStat":{"value":"1","label":"SACKS"},"summary":""}]},{"name":"totalTackles","displayName":"Tackles","leaders":[{"displayValue":"7","value":7.0,"athlete":{"id":"156310","uid":"s:20~l:23~a:156310","guid":"5ff04f25-566c-7cfd-3a52-fb1561e9d6d9","lastName":"Wolfe","fullName":"D.J. Wolfe","displayName":"D.J. Wolfe","shortName":"D.J. Wolfe","links":[{"rel":["playercard","desktop","athlete"],"href":"https://www.espn.com/college-football/player/_/id/156310/dj-wolfe","text":"Player Card"}],"jersey":"42 ","position":{"name":"Cornerback","displayName":"Cornerback","abbreviation":"CB"},"status":{"id":"2","name":"Inactive","type":"inactive","abbreviation":"Inactive"}},"mainStat":{"value":"7","label":"TOT"},"summary":"5 SOLO"}]}]},"2390":{"record":[{"type":"total","summary":"1-1","displayValue":"1-1"},{"type":"road","summary":"0-1","displayValue":"0-1"},{"type":"vsconf","summary":"0-0","displayValue":"0-0"}],"linescores":[{"displayValue":"3"},{"displayValue":"7"},{"displayValue":"3"},{"displayValue":"0"}],"statistics":[{"name":"firstDowns","displayValue":"7","value":7.0,"label":"1st Downs"},{"name":"thirdDownEff","displayValue":"3-17","value":0.1764705882,"label":"3rd down efficiency"},{"name":"fourthDownEff","displayValue":"1-1","value":1,"label":"4th down efficiency"},{"name":"totalYards","displayValue":"139","value":"-","label":"Total Yards"},{"name":"netPassingYards","displayValue":"99","value":99.0,"label":"Passing"},{"name":"completionAttempts","displayValue":"11/24","value":"-","label":"Comp/Att"},{"name":"yardsPerPass","displayValue":"3.6","value":3.625,"label":"Yards per pass"},{"name":"rushingYards","displayValue":"52","value":52.0,"label":"Rushing"},{"name":"rushingAttempts","displayValue":"35","value":35.0,"label":"Rushing Attempts"},{"name":"yardsPerRushAttempt","displayValue":"1.5","value":1.486,"label":"Yards per rush"},{"name":"totalPenaltiesYards","displayValue":"6-55","value":"-","label":"Penalties"},{"name":"turnovers","displayValue":"1","value":"-","label":"Turnovers"},{"name":"fumblesLost","displayValue":"1","value":1.0,"label":"Fumbles lost"},{"name":"interceptions","displayValue":"0","value":0.0,"label":"Interceptions thrown"},{"name":"possessionTime","displayValue":"16:09","value":969,"label":"Possession"}],"leaders":[{"name":"passingYards","displayName":"Passing Yards","leaders":[{"displayValue":"7/14, 65 YDS, 1 TD","value":65.0,"athlete":{"id":"146486","uid":"s:20~l:23~a:146486","guid":"d9bc18c7-d960-feb3-ba7c-b90154a0f33e","lastName":"Wright","fullName":"Kyle Wright","displayName":"Kyle Wright","shortName":"K. Wright","links":[{"rel":["playercard","desktop","athlete"],"href":"https://www.espn.com/college-football/player/_/id/146486/kyle-wright","text":"Player Card"}],"jersey":"3  ","position":{"name":"Quarterback","displayName":"Quarterback","abbreviation":"QB"},"status":{"id":"2","name":"Inactive","type":"inactive","abbreviation":"Inactive"}},"mainStat":{"value":"65","label":"YDS"},"summary":"7/14, 1 TD"}]},{"name":"rushingYards","displayName":"Rushing Yards","leaders":[{"displayValue":"8 CAR, 28 YDS","value":28.0,"athlete":{"id":"183687","uid":"s:20~l:23~a:183687","guid":"18cd3b94-7391-a878-5bab-968696925673","lastName":"James","fullName":"Javarris James","displayName":"Javarris James","shortName":"J. James","links":[{"rel":["playercard","desktop","athlete"],"href":"https://www.espn.com/college-football/player/_/id/183687/javarris-james","text":"Player Card"}],"position":{"name":"Unknown","displayName":"Unknown","abbreviation":"-"},"status":{"id":"2","name":"Inactive","type":"inactive","abbreviation":"Inactive"}},"mainStat":{"value":"28","label":"YDS"},"summary":"8 CAR"}]},{"name":"receivingYards","displayName":"Receiving Yards","leaders":[{"displayValue":"3 REC, 35 YDS","value":35.0,"athlete":{"id":"146476","uid":"s:20~l:23~a:146476","guid":"2823fae4-5b9e-1462-3c45-2024540fb216","lastName":"Jenkins","fullName":"Darnell Jenkins","displayName":"Darnell Jenkins","shortName":"D. Jenkins","links":[{"rel":["playercard","desktop","athlete"],"href":"https://www.espn.com/college-football/player/_/id/146476/darnell-jenkins","text":"Player Card"}],"jersey":"84 ","position":{"name":"Wide Receiver","displayName":"Wide Receiver","abbreviation":"WR"},"status":{"id":"2","name":"Inactive","type":"inactive","abbreviation":"Inactive"}},"mainStat":{"value":"35","label":"YDS"},"summary":"3 REC"}]},{"name":"sacks","displayName":"Sacks","leaders":[{"displayValue":"1","value":1.0,"athlete":{"id":"161106","uid":"s:20~l:23~a:161106","guid":"91ff5c77-5177-02bd-cc67-d131f591941b","lastName":"Campbell","fullName":"Calais Campbell","displayName":"Calais Campbell","shortName":"C. Campbell","links":[{"rel":["playercard","desktop","athlete"],"href":"https://www.espn.com/college-football/player/_/id/161106/calais-campbell","text":"Player Card"}],"jersey":"93 ","position":{"name":"Defensive End","displayName":"Defensive End","abbreviation":"DE"},"status":{"id":"2","name":"Inactive","type":"inactive","abbreviation":"Inactive"}},"mainStat":{"value":"1","label":"SACKS"},"summary":""}]},{"name":"totalTackles","displayName":"Tackles","leaders":[{"displayValue":"13","value":13.0,"athlete":{"id":"146495","uid":"s:20~l:23~a:146495","guid":"9aa0f203-b027-3b24-32fc-8dd26afeca26","lastName":"Gooden","fullName":"Tavares Gooden","displayName":"Tavares Gooden","shortName":"T. Gooden","links":[{"rel":["playercard","desktop","athlete"],"href":"https://www.espn.com/college-football/player/_/id/146495/tavares-gooden","text":"Player Card"}],"jersey":"56 ","position":{"name":"Linebacker","displayName":"Linebacker","abbreviation":"LB"},"status":{"id":"2","name":"Inactive","type":"inactive","abbreviation":"Inactive"}},"mainStat":{"value":"13","label":"TOT"},"summary":"7 SOLO"}]}]},"game_id":272510201,"season":2007,"week":2}