{"236":{"record":[{"type":"total","summary":"0-1","displayValue":"0-1"},{"type":"home","summary":"0-1","displayValue":"0-1"},{"type":"vsconf","summary":"0-0","displayValue":"0-0"}],"linescores":[{"displayValue":"10"},{"displayValue":"0"},{"displayValue":"3"},{"displayValue":"7"}],"statistics":[{"name":"firstDowns","displayValue":"11","value":11.0,"label":"1st Downs"},{"name":"thirdDownEff","displayValue":"4-12","value":0.3333333333,"label":"3rd down efficiency"},{"name":"fourthDownEff","displayValue":"0-2","value":0,"label":"4th down efficiency"},{"name":"totalYards","displayValue":"196","value":"-","label":"Total Yards"},{"name":"netPassingYards","displayValue":"86","value":86.0,"label":"Passing"},{"name":"completionAttempts","displayValue":"9/16","value":"-","label":"Comp/Att"},{"name":"yardsPerPass","displayValue":"5.4","value":5.375,"label":"Yards per pass"},{"name":"rushingYards","displayValue":"110","value":110.0,"label":"Rushing"},{"name":"rushingAttempts","displayValue":"36","value":36.0,"label":"Rushing Attempts"},{"name":"yardsPerRushAttempt","displayValue":"3.1","value":3.056,"label":"Yards per rush"},{"name":"totalPenaltiesYards","displayValue":"4-42","value":"-","label":"Penalties"},{"name":"turnovers","displayValue":"1","value":"-","label":"Turnovers"},{"name":"fumblesLost","displayValue":"0","value":0.0,"label":"Fumbles lost"},{"name":"interceptions","displayValue":"1","value":1.0,"label":"Interceptions thrown"},{"name":"possessionTime","displayValue":"25:39","value":1539,"label":"Possession"}],"leaders":[{"name":"passingYards","displayName":"Passing Yards","leaders":[{"displayValue":"9/16, 86 YDS, 1 INT","value":86.0,"athlete":{"id":"512913","uid":"s:20~l:23~a:512913","guid":"14f354fc-52c4-b2ff-a6b8-04e4cc8f6e9b","lastName":"Huesman","fullName":"Jacob Huesman","displayName":"Jacob Huesman","shortName":"J. Huesman","links":[{"rel":["playercard","desktop","athlete"],"href":"https://www.espn.com/college-football/player/_/id/512913/jacob-huesman","text":"Player Card"}],"jersey":"14","position":{"name":"Quarterback","displayName":"Quarterback","abbreviation":"QB"},"status":{"id":"2","name":"Inactive","type":"inactive","abbreviation":"Inactive"}},"mainStat":{"value":"86","label":"YDS"},"summary":"9/16, 1 INT"}]},{"name":"rushingYards","displayName":"Rushing Yards","leaders":[{"displayValue":"12 CAR, 59 YDS","value":59.0,"athlete":{"id":"548480","uid":"s:20~l:23~a:548480","guid":"a32a4a5a-02ae-2ce9-32d9-ec25df3d9d85","lastName":"Craine","fullName":"Derrick Craine","displayName":"Derrick Craine","shortName":"D. Craine","links":[{"rel":["playercard","desktop","athlete"],"href":"https://www.espn.com/college-football/player/_/id/548480/derrick-craine","text":"Player Card"}],"jersey":"34","position":{"name":"Running Back","displayName":"Running Back","abbreviation":"RB"},"status":{"id":"2","name":"Inactive","type":"inactive","abbreviation":"Inactive"}},"mainStat":{"value":"59","label":"YDS"},"summary":"12 CAR"}]},{"name":"receivingYards","displayName":"Receiving Yards","leaders":[{"displayValue":"3 REC, 49 YDS","value":49.0,"athlete":{"id":"3131771","uid":"s:20~l:23~a:3131771","guid":"ca40238e-f36d-3413-163a-e123c0366454","lastName":"Bagley","fullName":"Richardre Bagley","displayName":"Richardre Bagley","shortName":"R. Bagley","links":[{"rel":["playercard","desktop","athlete"],"href":"https://www.espn.com/college-football/player/_/id/3131771/richardre-bagley","text":"Player Card"}],"jersey":"23","position":{"name":"Running Back","displayName":"Running Back","abbreviation":"RB"},"status":{"id":"2","name":"Inactive","type":"inactive","abbreviation":"Inactive"}},"mainStat":{"value":"49","label":"YDS"},"summary":"3 REC"}]},{"name":"sacks","displayName":"Sacks"},{"name":"totalTackles","displayName":"Tackles"}]},"55":{"record":[{"type":"total","summary":"1-0","displayValue":"1-0"},{"type":"road","summary":"1-0","displayValue":"1-0"},{"type":"vsconf","summary":"0-0","displayValue":"0-0"}],"linescores":[{"displayValue":"3"},{"displayValue":"7"},{"displayValue":"3"},{"displayValue":"10"}],"statistics":[{"name":"firstDowns","displayValue":"17","value":17.0,"label":"1st Downs"},{"name":"thirdDownEff","displayValue":"3-15","value":0.2,"label":"3rd down efficiency"},{"name":"fourthDownEff","displayValue":"3-3","value":1,"label":"4th down efficiency"},{"name":"totalYards","displayValue":"411","value":"-","label":"Total Yards"},{"name":"netPassingYards","displayValue":"113","value":113.0,"label":"Passing"},{"name":"completionAttempts","displayValue":"16/24","value":"-","label":"Comp/Att"},{"name":"yardsPerPass","displayValue":"4.7","value":4.708,"label":"Yards per pass"},{"name":"rushingYards","displayValue":"298","value":298.0,"label":"Rushing"},{"name":"rushingAttempts","displayValue":"44","value":44.0,"label":"Rushing Attempts"},{"name":"yardsPerRushAttempt","displayValue":"6.8","value":6.773,"label":"Yards per rush"},{"name":"totalPenaltiesYards","displayValue":"8-50","value":"-","label":"Penalties"},{"name":"turnovers","displayValue":"1","value":"-","label":"Turnovers"},{"name":"fumblesLost","displayValue":"1","value":1.0,"label":"Fumbles lost"},{"name":"interceptions","displayValue":"0","value":0.0,"label":"Interceptions thrown"},{"name":"possessionTime","displayValue":"34:21","value":2061,"label":"Possession"}],"leaders":[{"name":"passingYards","displayName":"Passing Yards","leaders":[{"displayValue":"16/24, 113 YDS, 1 TD","value":113.0,"athlete":{"id":"537200","uid":"s:20~l:23~a:537200","guid":"cdec8e33-70c3-372d-5bb3-13106830186e","lastName":"Jenkins","fullName":"Eli Jenkins","displayName":"Eli Jenkins","shortName":"E. Jenkins","links":[{"rel":["playercard","desktop","athlete"],"href":"https://www.espn.com/college-football/player/_/id/537200/eli-jenkins","text":"Player Card"}],"jersey":"7","position":{"name":"Quarterback","displayName":"Quarterback","abbreviation":"QB"},"status":{"id":"2","name":"Inactive","type":"inactive","abbreviation":"Inactive"}},"mainStat":{"value":"113","label":"YDS"},"summary":"16/24, 1 TD"}]},{"name":"rushingYards","displayName":"Rushing Yards","leaders":[{"displayValue":"15 CAR, 173 YDS","value":173.0,"athlete":{"id":"537205","uid":"s:20~l:23~a:537205","guid":"e59dca5f-3cb9-1de9-49f2-7d54ab8787ba","lastName":"Pope","fullName":"Troymaine Pope","displayName":"Troymaine Pope","shortName":"T. Pope","links":[{"rel":["playercard","desktop","athlete"],"href":"https://www.espn.com/college-football/player/_/id/537205/troymaine-pope","text":"Player Card"}],"jersey":"24","position":{"name":"Running Back","displayName":"Running Back","abbreviation":"RB"},"status":{"id":"2","name":"Inactive","type":"inactive","abbreviation":"Inactive"}},"mainStat":{"value":"173","label":"YDS"},"summary":"15 CAR"}]},{"name":"receivingYards","displayName":"Receiving Yards","leaders":[{"displayValue":"8 REC, 52 YDS","value":52.0,"athlete":{"id":"537203","uid":"s:20~l:23~a:537203","guid":"10b49a4d-46a4-f4a4-a2ae-e5ddf80455d1","lastName":"Barge","fullName":"Josh Barge","displayName":"Josh Barge","shortName":"J. Barge","links":[{"rel":["playercard","desktop","athlete"],"href":"https://www.espn.com/college-football/player/_/id/537203/josh-barge","text":"Player Card"}],"jersey":"12","position":{"name":"Wide Receiver","displayName":"Wide Receiver","abbreviation":"WR"},"status":{"id":"2","name":"Inactive","type":"inactive","abbreviation":"Inactive"}},"mainStat":{"value":"52","label":"YDS"},"summary":"8 REC"}]},{"name":"sacks","displayName":"Sacks"},{"name":"totalTackles","displayName":"Tackles"}]},"game_id":400795768,"season":2015,"week":1}