{"2636":{"record":[{"type":"total","summary":"2-4","displayValue":"2-4"},{"type":"home","summary":"1-2","displayValue":"1-2"},{"type":"vsconf","summary":"1-2","displayValue":"1-2"}],"linescores":[{"displayValue":"0"},{"displayValue":"7"},{"displayValue":"7"},{"displayValue":"0"}],"statistics":[{"name":"firstDowns","displayValue":"12","value":12.0,"label":"1st Downs"},{"name":"thirdDownEff","displayValue":"4-13","value":0.3076923077,"label":"3rd down efficiency"},{"name":"fourthDownEff","displayValue":"0-2","value":0,"label":"4th down efficiency"},{"name":"totalYards","displayValue":"220","value":"-","label":"Total Yards"},{"name":"netPassingYards","displayValue":"94","value":94.0,"label":"Passing"},{"name":"completionAttempts","displayValue":"8/20","value":"-","label":"Comp/Att"},{"name":"yardsPerPass","displayValue":"4.7","value":4.7,"label":"Yards per pass"},{"name":"rushingYards","displayValue":"126","value":126.0,"label":"Rushing"},{"name":"rushingAttempts","displayValue":"36","value":36.0,"label":"Rushing Attempts"},{"name":"yardsPerRushAttempt","displayValue":"3.5","value":3.5,"label":"Yards per rush"},{"name":"totalPenaltiesYards","displayValue":"9-78","value":"-","label":"Penalties"},{"name":"turnovers","displayValue":"2","value":"-","label":"Turnovers"},{"name":"fumblesLost","displayValue":"2","value":2.0,"label":"Fumbles lost"},{"name":"interceptions","displayValue":"0","value":0.0,"label":"Interceptions thrown"},{"name":"possessionTime","displayValue":"23:54","value":1434,"label":"Possession"}],"leaders":[{"name":"passingYards","displayName":"Passing Yards","leaders":[{"displayValue":"8/19, 94 YDS","value":94.0,"athlete":{"id":"4242203","uid":"s:20~l:23~a:4242203","guid":"71544732-8553-5acd-383d-cb4dfa74b749","lastName":"Narcisse","fullName":"Lowell Narcisse","displayName":"Lowell Narcisse","shortName":"L. Narcisse","links":[{"rel":["playercard","desktop","athlete"],"href":"https://www.espn.com/college-football/player/_/id/4242203/lowell-narcisse","text":"Player Card"}],"headshot":{"href":"https://a.espncdn.com/i/headshots/college-football/players/full/4242203.png","alt":"Lowell Narcisse"},"jersey":"10","position":{"name":"Quarterback","displayName":"Quarterback","abbreviation":"QB"},"status":{"id":"2","name":"Inactive","type":"inactive","abbreviation":"Inactive"}},"mainStat":{"value":"94","label":"YDS"},"summary":"8/19"}]},{"name":"rushingYards","displayName":"Rushing Yards","leaders":[{"displayValue":"18 CAR, 86 YDS, 1 TD","value":86.0,"athlete":{"id":"4242203","uid":"s:20~l:23~a:4242203","guid":"71544732-8553-5acd-383d-cb4dfa74b749","lastName":"Narcisse","fullName":"Lowell Narcisse","displayName":"Lowell Narcisse","shortName":"L. Narcisse","links":[{"rel":["playercard","desktop","athlete"],"href":"https://www.espn.com/college-football/player/_/id/4242203/lowell-narcisse","text":"Player Card"}],"headshot":{"href":"https://a.espncdn.com/i/headshots/college-football/players/full/4242203.png","alt":"Lowell Narcisse"},"jersey":"10","position":{"name":"Quarterback","displayName":"Quarterback","abbreviation":"QB"},"status":{"id":"2","name":"Inactive","type":"inactive","abbreviation":"Inactive"}},"mainStat":{"value":"86","label":"YDS"},"summary":"18 CAR, 1 TD"}]},{"name":"receivingYards","displayName":"Receiving Yards","leaders":[{"displayValue":"2 REC, 41 YDS","value":41.0,"athlete":{"id":"3864258","uid":"s:20~l:23~a:3864258","guid":"5ba368d4-f1d4-1903-a313-3c754c6d5419","lastName":"Strickland II","fullName":"Carlos Strickland II","displayName":"Carlos Strickland II","shortName":"C. Strickland II","links":[{"rel":["playercard","desktop","athlete"],"href":"https://www.espn.com/college-football/player/_/id/3864258/carlos-strickland-ii","text":"Player Card"}],"headshot":{"href":"https://a.espncdn.com/i/headshots/college-football/players/full/3864258.png","alt":"Carlos Strickland II"},"jersey":"85","position":{"name":"Tight End","displayName":"Tight End","abbreviation":"TE"},"status":{"id":"2","name":"Inactive","type":"inactive","abbreviation":"Inactive"}},"mainStat":{"value":"41","label":"YDS"},"summary":"2 REC"}]},{"name":"sacks","displayName":"Sacks"},{"name":"totalTackles","displayName":"Tackles","leaders":[{"displayValue":"8","value":8.0,"athlete":{"id":"4570021","uid":"s:20~l:23~a:4570021","guid":"d554b9a1-be99-b89d-0889-22d03eb10ee3","lastName":"Harmanson","fullName":"Trevor Harmanson","displayName":"Trevor Harmanson","shortName":"T. Harmanson","links":[{"rel":["playercard","desktop","athlete"],"href":"https://www.espn.com/college-football/player/_/id/4570021/trevor-harmanson","text":"Player Card"}],"headshot":{"href":"https://a.espncdn.com/i/headshots/college-football/players/full/4570021.png","alt":"Trevor Harmanson"},"jersey":"1","position":{"name":"Linebacker","displayName":"Linebacker","abbreviation":"LB"},"status":{"id":"2","name":"Inactive","type":"inactive","abbreviation":"Inactive"}},"mainStat":{"value":"8","label":"TOT"},"summary":"6 SOLO"}]}]},"5":{"record":[{"type":"total","summary":"5-1","displayValue":"5-1"},{"type":"road","summary":"2-1","displayValue":"2-1"},{"type":"vsconf","summary":"2-1","displayValue":"2-1"}],"linescores":[{"displayValue":"3"},{"displayValue":"13"},{"displayValue":"7"},{"displayValue":"10"}],"statistics":[{"name":"firstDowns","displayValue":"26","value":26.0,"label":"1st Downs"},{"name":"thirdDownEff","displayValue":"2-11","value":0.1818181818,"label":"3rd down efficiency"},{"name":"fourthDownEff","displayValue":"1-2","value":0.5,"label":"4th down efficiency"},{"name":"totalYards","displayValue":"492","value":"-","label":"Total Yards"},{"name":"netPassingYards","displayValue":"294","value":294.0,"label":"Passing"},{"name":"completionAttempts","displayValue":"17/26","value":"-","label":"Comp/Att"},{"name":"yardsPerPass","displayValue":"11.3","value":11.308,"label":"Yards per pass"},{"name":"rushingYards","displayValue":"198","value":198.0,"label":"Rushing"},{"name":"rushingAttempts","displayValue":"41","value":41.0,"label":"Rushing Attempts"},{"name":"yardsPerRushAttempt","displayValue":"4.8","value":4.829,"label":"Yards per rush"},{"name":"totalPenaltiesYards","displayValue":"6-68","value":"-","label":"Penalties"},{"name":"turnovers","displayValue":"2","value":"-","label":"Turnovers"},{"name":"fumblesLost","displayValue":"1","value":1.0,"label":"Fumbles lost"},{"name":"interceptions","displayValue":"1","value":1.0,"label":"Interceptions thrown"},{"name":"possessionTime","displayValue":"36:06","value":2166,"label":"Possession"}],"leaders":[{"name":"passingYards","displayName":"Passing Yards","leaders":[{"displayValue":"17/26, 294 YDS, 2 TD, 1 INT","value":294.0,"athlete":{"id":"4239793","uid":"s:20~l:23~a:4239793","guid":"ccd81a18-cc88-2ca8-232f-65a96fc638d5","lastName":"Johnston III","fullName":"Tyler Johnston III","displayName":"Tyler Johnston III","shortName":"T. Johnston III","links":[{"rel":["playercard","desktop","athlete"],"href":"https://www.espn.com/college-football/player/_/id/4239793/tyler-johnston-iii","text":"Player Card"}],"headshot":{"href":"https://a.espncdn.com/i/headshots/college-football/players/full/4239793.png","alt":"Tyler Johnston III"},"jersey":"17","position":{"name":"Quarterback","displayName":"Quarterback","abbreviation":"QB"},"status":{"id":"2","name":"Inactive","type":"inactive","abbreviation":"Inactive"}},"mainStat":{"value":"294","label":"YDS"},"summary":"17/26, 2 TD, 1 INT"}]},{"name":"rushingYards","displayName":"Rushing Yards","leaders":[{"displayValue":"13 CAR, 92 YDS, 1 TD","value":92.0,"athlete":{"id":"4239821","uid":"s:20~l:23~a:4239821","guid":"18ecd3be-8c1a-9dc7-511b-9418a0111a3d","lastName":"Stanley","fullName":"Lucious Stanley","displayName":"Lucious Stanley","shortName":"L. Stanley","links":[{"rel":["playercard","desktop","athlete"],"href":"https://www.espn.com/college-football/player/_/id/4239821/lucious-stanley","text":"Player Card"}],"headshot":{"href":"https://a.espncdn.com/i/headshots/college-football/players/full/4239821.png","alt":"Lucious Stanley"},"jersey":"24","position":{"name":"Running Back","displayName":"Running Back","abbreviation":"RB"},"status":{"id":"2","name":"Inactive","type":"inactive","abbreviation":"Inactive"}},"mainStat":{"value":"92","label":"YDS"},"summary":"13 CAR, 1 TD"}]},{"name":"receivingYards","displayName":"Receiving Yards","leaders":[{"displayValue":"6 REC, 167 YDS, 1 TD","value":167.0,"athlete":{"id":"4363409","uid":"s:20~l:23~a:4363409","guid":"d368d872-8ec7-fa92-7cb7-f867689233a0","lastName":"Watkins Jr.","fullName":"Austin Watkins Jr.","displayName":"Austin Watkins Jr.","shortName":"A. Watkins Jr.","links":[{"rel":["playercard","desktop","athlete"],"href":"https://www.espn.com/college-football/player/_/id/4363409/austin-watkins-jr","text":"Player Card"}],"headshot":{"href":"https://a.espncdn.com/i/headshots/college-football/players/full/4363409.png","alt":"Austin Watkins Jr."},"jersey":"6","position":{"name":"Wide Receiver","displayName":"Wide Receiver","abbreviation":"WR"},"status":{"id":"2","name":"Inactive","type":"inactive","abbreviation":"Inactive"}},"mainStat":{"value":"167","label":"YDS"},"summary":"6 REC, 1 TD"}]},{"name":"sacks","displayName":"Sacks","leaders":[{"displayValue":"1.5","value":1.5,"athlete":{"id":"4034957","uid":"s:20~l:23~a:4034957","guid":"1408eab2-7ecc-08e2-845d-b3d41d7260f8","lastName":"Smith","fullName":"Jordan Smith","displayName":"Jordan Smith","shortName":"J. Smith","links":[{"rel":["playercard","desktop","athlete"],"href":"https://www.espn.com/college-football/player/_/id/4034957/jordan-smith","text":"Player Card"}],"headshot":{"href":"https://a.espncdn.com/i/headshots/college-football/players/full/4034957.png","alt":"Jordan Smith"},"jersey":"22","position":{"name":"Linebacker","displayName":"Linebacker","abbreviation":"LB"},"status":{"id":"2","name":"Inactive","type":"inactive","abbreviation":"Inactive"}},"mainStat":{"value":"1.5","label":"SACKS"},"summary":""}]},{"name":"totalTackles","displayName":"Tackles","leaders":[{"displayValue":"7","value":7.0,"athlete":{"id":"4239805","uid":"s:20~l:23~a:4239805","guid":"00b10807-1e32-683e-1c9e-dce1b09c40a6","lastName":"Moll","fullName":"Kristopher Moll","displayName":"Kristopher Moll","shortName":"K. Moll","links":[{"rel":["playercard","desktop","athlete"],"href":"https://www.espn.com/college-football/player/_/id/4239805/kristopher-moll","text":"Player Card"}],"headshot":{"href":"https://a.espncdn.com/i/headshots/college-football/players/full/4239805.png","alt":"Kristopher Moll"},"jersey":"9","position":{"name":"Linebacker","displayName":"Linebacker","abbreviation":"LB"},"status":{"id":"2","name":"Inactive","type":"inactive","abbreviation":"Inactive"}},"mainStat":{"value":"7","label":"TOT"},"summary":"5 SOLO"}]}]},"game_id":401114284,"season":2019,"week":7}