{"2579":{"record":[{"type":"total","summary":"2-2","displayValue":"2-2"},{"type":"home","summary":"1-1","displayValue":"1-1"},{"type":"vsconf","summary":"0-2","displayValue":"0-2"}],"linescores":[{"displayValue":"0"},{"displayValue":"0"},{"displayValue":"7"},{"displayValue":"3"}],"statistics":[{"name":"firstDowns","displayValue":"12","value":12.0,"label":"1st Downs"},{"name":"thirdDownEff","displayValue":"3-12","value":0.25,"label":"3rd down efficiency"},{"name":"fourthDownEff","displayValue":"0-3","value":0,"label":"4th down efficiency"},{"name":"totalYards","displayValue":"216","value":"-","label":"Total Yards"},{"name":"netPassingYards","displayValue":"158","value":158.0,"label":"Passing"},{"name":"completionAttempts","displayValue":"17/25","value":"-","label":"Comp/Att"},{"name":"yardsPerPass","displayValue":"6.3","value":6.32,"label":"Yards per pass"},{"name":"rushingYards","displayValue":"58","value":58.0,"label":"Rushing"},{"name":"rushingAttempts","displayValue":"26","value":26.0,"label":"Rushing Attempts"},{"name":"yardsPerRushAttempt","displayValue":"2.2","value":2.231,"label":"Yards per rush"},{"name":"totalPenaltiesYards","displayValue":"5-45","value":"-","label":"Penalties"},{"name":"turnovers","displayValue":"0","value":"-","label":"Turnovers"},{"name":"fumblesLost","displayValue":"0","value":0.0,"label":"Fumbles lost"},{"name":"interceptions","displayValue":"0","value":0.0,"label":"Interceptions thrown"},{"name":"possessionTime","displayValue":"24:24","value":1464,"label":"Possession"}],"leaders":[{"name":"passingYards","displayName":"Passing Yards","leaders":[{"displayValue":"17/25, 158 YDS, 1 TD","value":158.0,"athlete":{"id":"4429079","uid":"s:20~l:23~a:4429079","guid":"453101fe-def9-3542-adb7-a7650d41d4ec","lastName":"Doty","fullName":"Luke Doty","displayName":"Luke Doty","shortName":"L. Doty","links":[{"rel":["playercard","desktop","athlete"],"href":"https://www.espn.com/college-football/player/_/id/4429079/luke-doty","text":"Player Card"}],"headshot":{"href":"https://a.espncdn.com/i/headshots/college-football/players/full/4429079.png","alt":"Luke Doty"},"jersey":"9","position":{"name":"Wide Receiver","displayName":"Wide Receiver","abbreviation":"WR"},"status":{"id":"1","name":"Active","type":"active","abbreviation":"Active"}},"mainStat":{"value":"158","label":"YDS"},"summary":"17/25, 1 TD"}]},{"name":"rushingYards","displayName":"Rushing Yards","leaders":[{"displayValue":"12 CAR, 38 YDS","value":38.0,"athlete":{"id":"4570674","uid":"s:20~l:23~a:4570674","guid":"6541ec20-1b1f-efd3-e3dc-d306b88a5f63","lastName":"Harris","fullName":"Kevin Harris","displayName":"Kevin Harris","shortName":"K. Harris","links":[{"rel":["playercard","desktop","athlete"],"href":"https://www.espn.com/college-football/player/_/id/4570674/kevin-harris","text":"Player Card"}],"headshot":{"href":"https://a.espncdn.com/i/headshots/college-football/players/full/4570674.png","alt":"Kevin Harris"},"jersey":"20","position":{"name":"Running Back","displayName":"Running Back","abbreviation":"RB"},"status":{"id":"2","name":"Inactive","type":"inactive","abbreviation":"Inactive"}},"mainStat":{"value":"38","label":"YDS"},"summary":"12 CAR"}]},{"name":"receivingYards","displayName":"Receiving Yards","leaders":[{"displayValue":"4 REC, 63 YDS, 1 TD","value":63.0,"athlete":{"id":"4692835","uid":"s:20~l:23~a:4692835","guid":"24cf72d7-f9aa-3d1d-b71b-5f9083110c0b","lastName":"Brooks","fullName":"Jalen Brooks","displayName":"Jalen Brooks","shortName":"J. Brooks","links":[{"rel":["playercard","desktop","athlete"],"href":"https://www.espn.com/college-football/player/_/id/4692835/jalen-brooks","text":"Player Card"}],"headshot":{"href":"https://a.espncdn.com/i/headshots/college-football/players/full/4692835.png","alt":"Jalen Brooks"},"jersey":"13","position":{"name":"Wide Receiver","displayName":"Wide Receiver","abbreviation":"WR"},"status":{"id":"2","name":"Inactive","type":"inactive","abbreviation":"Inactive"}},"mainStat":{"value":"63","label":"YDS"},"summary":"4 REC, 1 TD"}]},{"name":"sacks","displayName":"Sacks"},{"name":"totalTackles","displayName":"Tackles","leaders":[{"displayValue":"12","value":12.0,"athlete":{"id":"4029790","uid":"s:20~l:23~a:4029790","guid":"36d9059b-bf3e-ef16-c48f-48455c4065f9","lastName":"Foster","fullName":"Jaylan Foster","displayName":"Jaylan Foster","shortName":"J. Foster","links":[{"rel":["playercard","desktop","athlete"],"href":"https://www.espn.com/college-football/player/_/id/4029790/jaylan-foster","text":"Player Card"}],"headshot":{"href":"https://a.espncdn.com/i/headshots/college-football/players/full/4029790.png","alt":"Jaylan Foster"},"jersey":"12","position":{"name":"Defensive Back","displayName":"Defensive Back","abbreviation":"DB"},"status":{"id":"2","name":"Inactive","type":"inactive","abbreviation":"Inactive"}},"mainStat":{"value":"12","label":"TOT"},"summary":"4 SOLO"}]}]},"96":{"record":[{"type":"total","summary":"4-0","displayValue":"4-0"},{"type":"road","summary":"1-0","displayValue":"1-0"},{"type":"vsconf","summary":"2-0","displayValue":"2-0"}],"linescores":[{"displayValue":"7"},{"displayValue":"3"},{"displayValue":"3"},{"displayValue":"3"}],"statistics":[{"name":"firstDowns","displayValue":"22","value":22.0,"label":"1st Downs"},{"name":"thirdDownEff","displayValue":"6-12","value":0.5,"label":"3rd down efficiency"},{"name":"fourthDownEff","displayValue":"0-0","value":"-","label":"4th down efficiency"},{"name":"totalYards","displayValue":"332","value":"-","label":"Total Yards"},{"name":"netPassingYards","displayValue":"102","value":102.0,"label":"Passing"},{"name":"completionAttempts","displayValue":"15/22","value":"-","label":"Comp/Att"},{"name":"yardsPerPass","displayValue":"4.6","value":4.636,"label":"Yards per pass"},{"name":"rushingYards","displayValue":"230","value":230.0,"label":"Rushing"},{"name":"rushingAttempts","displayValue":"44","value":44.0,"label":"Rushing Attempts"},{"name":"yardsPerRushAttempt","displayValue":"5.2","value":5.227,"label":"Yards per rush"},{"name":"totalPenaltiesYards","displayValue":"4-29","value":"-","label":"Penalties"},{"name":"turnovers","displayValue":"3","value":"-","label":"Turnovers"},{"name":"fumblesLost","displayValue":"2","value":2.0,"label":"Fumbles lost"},{"name":"interceptions","displayValue":"1","value":1.0,"label":"Interceptions thrown"},{"name":"possessionTime","displayValue":"35:36","value":2136,"label":"Possession"}],"leaders":[{"name":"passingYards","displayName":"Passing Yards","leaders":[{"displayValue":"15/22, 102 YDS, 1 INT","value":102.0,"athlete":{"id":"4361418","uid":"s:20~l:23~a:4361418","guid":"31a5ae70-e664-9c6a-ec3e-c407bf56f321","lastName":"Levis","fullName":"Will Levis","displayName":"Will Levis","shortName":"W. Levis","links":[{"rel":["playercard","desktop","athlete"],"href":"https://www.espn.com/college-football/player/_/id/4361418/will-levis","text":"Player Card"}],"headshot":{"href":"https://a.espncdn.com/i/headshots/college-football/players/full/4361418.png","alt":"Will Levis"},"jersey":"7","position":{"name":"Quarterback","displayName":"Quarterback","abbreviation":"QB"},"status":{"id":"2","name":"Inactive","type":"inactive","abbreviation":"Inactive"}},"mainStat":{"value":"102","label":"YDS"},"summary":"15/22, 1 INT"}]},{"name":"rushingYards","displayName":"Rushing Yards","leaders":[{"displayValue":"26 CAR, 144 YDS","value":144.0,"athlete":{"id":"4362619","uid":"s:20~l:23~a:4362619","guid":"6e206853-654e-64b6-48fb-544f0353705e","lastName":"Rodriguez Jr.","fullName":"Chris Rodriguez Jr.","displayName":"Chris Rodriguez Jr.","shortName":"C. Rodriguez Jr.","links":[{"rel":["playercard","desktop","athlete"],"href":"https://www.espn.com/college-football/player/_/id/4362619/chris-rodriguez-jr","text":"Player Card"}],"headshot":{"href":"https://a.espncdn.com/i/headshots/college-football/players/full/4362619.png","alt":"Chris Rodriguez Jr."},"jersey":"24","position":{"name":"Running Back","displayName":"Running Back","abbreviation":"RB"},"status":{"id":"2","name":"Inactive","type":"inactive","abbreviation":"Inactive"}},"mainStat":{"value":"144","label":"YDS"},"summary":"26 CAR"}]},{"name":"receivingYards","displayName":"Receiving Yards","leaders":[{"displayValue":"7 REC, 65 YDS","value":65.0,"athlete":{"id":"4569587","uid":"s:20~l:23~a:4569587","guid":"8dc02010-f5af-f9d0-a382-58bd2200ae8d","lastName":"Robinson","fullName":"Wan'Dale Robinson","displayName":"Wan'Dale Robinson","shortName":"W. Robinson","links":[{"rel":["playercard","desktop","athlete"],"href":"https://www.espn.com/college-football/player/_/id/4569587/wandale-robinson","text":"Player Card"}],"headshot":{"href":"https://a.espncdn.com/i/headshots/college-football/players/full/4569587.png","alt":"Wan'Dale Robinson"},"jersey":"1","position":{"name":"Wide Receiver","displayName":"Wide Receiver","abbreviation":"WR"},"status":{"id":"2","name":"Inactive","type":"inactive","abbreviation":"Inactive"}},"mainStat":{"value":"65","label":"YDS"},"summary":"7 REC"}]},{"name":"sacks","displayName":"Sacks","leaders":[{"displayValue":"1","value":1.0,"athlete":{"id":"4428817","uid":"s:20~l:23~a:4428817","guid":"e847f180-e9b2-9d65-0d4d-397ae11cce3e","lastName":"Weaver","fullName":"J.J. Weaver","displayName":"J.J. Weaver","shortName":"J.J. Weaver","links":[{"rel":["playercard","desktop","athlete"],"href":"https://www.espn.com/college-football/player/_/id/4428817/jj-weaver","text":"Player Card"}],"headshot":{"href":"https://a.espncdn.com/i/headshots/college-football/players/full/4428817.png","alt":"J.J. Weaver"},"jersey":"13","position":{"name":"EDGE","displayName":"EDGE","abbreviation":"EDGE"},"status":{"id":"2","name":"Inactive","type":"inactive","abbreviation":"Inactive"}},"mainStat":{"value":"1","label":"SACKS"},"summary":""}]},{"name":"totalTackles","displayName":"Tackles","leaders":[{"displayValue":"8","value":8.0,"athlete":{"id":"4362621","uid":"s:20~l:23~a:4362621","guid":"77b6db1b-65e6-e29a-c52c-a9effc0b1eb4","lastName":"Square","fullName":"DeAndre Square","displayName":"DeAndre Square","shortName":"D. Square","links":[{"rel":["playercard","desktop","athlete"],"href":"https://www.espn.com/college-football/player/_/id/4362621/deandre-square","text":"Player Card"}],"headshot":{"href":"https://a.espncdn.com/i/headshots/college-football/players/full/4362621.png","alt":"DeAndre Square"},"jersey":"5","position":{"name":"Linebacker","displayName":"Linebacker","abbreviation":"LB"},"status":{"id":"2","name":"Inactive","type":"inactive","abbreviation":"Inactive"}},"mainStat":{"value":"8","label":"TOT"},"summary":"5 SOLO"}]}]},"game_id":401282087,"season":2021,"week":4}