{"2084":{"record":[{"type":"total","summary":"2-1","displayValue":"2-1"},{"type":"home","summary":"2-0","displayValue":"2-0"},{"type":"vsconf","summary":"0-0","displayValue":"0-0"}],"linescores":[{"displayValue":"7"},{"displayValue":"3"},{"displayValue":"17"},{"displayValue":"7"}],"statistics":[{"name":"firstDowns","displayValue":"15","value":15.0,"label":"1st Downs"},{"name":"thirdDownEff","displayValue":"6-14","value":0.4285714286,"label":"3rd down efficiency"},{"name":"fourthDownEff","displayValue":"1-1","value":1,"label":"4th down efficiency"},{"name":"totalYards","displayValue":"314","value":"-","label":"Total Yards"},{"name":"netPassingYards","displayValue":"185","value":185.0,"label":"Passing"},{"name":"completionAttempts","displayValue":"14/22","value":"-","label":"Comp/Att"},{"name":"yardsPerPass","displayValue":"8.4","value":8.409,"label":"Yards per pass"},{"name":"rushingYards","displayValue":"129","value":129.0,"label":"Rushing"},{"name":"rushingAttempts","displayValue":"38","value":38.0,"label":"Rushing Attempts"},{"name":"yardsPerRushAttempt","displayValue":"3.4","value":3.395,"label":"Yards per rush"},{"name":"totalPenaltiesYards","displayValue":"4-21","value":"-","label":"Penalties"},{"name":"turnovers","displayValue":"1","value":"-","label":"Turnovers"},{"name":"fumblesLost","displayValue":"1","value":1.0,"label":"Fumbles lost"},{"name":"interceptions","displayValue":"0","value":0.0,"label":"Interceptions thrown"},{"name":"possessionTime","displayValue":"27:56","value":1676,"label":"Possession"}],"leaders":[{"name":"passingYards","displayName":"Passing Yards","leaders":[{"displayValue":"14/22, 185 YDS, 1 TD","value":185.0,"athlete":{"id":"4877296","uid":"s:20~l:23~a:4877296","guid":"da75b212-6f9c-342a-9a68-4e33ea25f38c","lastName":"Ogbonna","fullName":"C.J. Ogbonna","displayName":"C.J. Ogbonna","shortName":"C.J. Ogbonna","links":[{"rel":["playercard","desktop","athlete"],"href":"https://www.espn.com/college-football/player/_/id/4877296/cj-ogbonna","text":"Player Card"}],"headshot":{"href":"https://a.espncdn.com/i/headshots/college-football/players/full/4877296.png","alt":"C.J. Ogbonna"},"jersey":"7","position":{"name":"Quarterback","displayName":"Quarterback","abbreviation":"QB"},"status":{"id":"2","name":"Inactive","type":"inactive","abbreviation":"Inactive"}},"mainStat":{"value":"185","label":"YDS"},"summary":"14/22, 1 TD"}]},{"name":"rushingYards","displayName":"Rushing Yards","leaders":[{"displayValue":"16 CAR, 86 YDS, 1 TD","value":86.0,"athlete":{"id":"5091891","uid":"s:20~l:23~a:5091891","guid":"fb973ed2-a187-38a5-b828-05c99f1243af","lastName":"Sperling","fullName":"Lamar Sperling","displayName":"Lamar Sperling","shortName":"L. Sperling","links":[{"rel":["playercard","desktop","athlete"],"href":"https://www.espn.com/college-football/player/_/id/5091891/lamar-sperling","text":"Player Card"}],"headshot":{"href":"https://a.espncdn.com/i/headshots/college-football/players/full/5091891.png","alt":"Lamar Sperling"},"jersey":"32","position":{"name":"Running Back","displayName":"Running Back","abbreviation":"RB"},"status":{"id":"1","name":"Active","type":"active","abbreviation":"Active"}},"mainStat":{"value":"86","label":"YDS"},"summary":"16 CAR, 1 TD"}]},{"name":"receivingYards","displayName":"Receiving Yards","leaders":[{"displayValue":"2 REC, 44 YDS, 1 TD","value":44.0,"athlete":{"id":"4571114","uid":"s:20~l:23~a:4571114","guid":"a0da97a7-5dfe-dff8-38b1-2140eb901f4e","lastName":"Jenkins","fullName":"JJ Jenkins","displayName":"JJ Jenkins","shortName":"J. Jenkins","links":[{"rel":["playercard","desktop","athlete"],"href":"https://www.espn.com/college-football/player/_/id/4571114/jj-jenkins","text":"Player Card"}],"headshot":{"href":"https://a.espncdn.com/i/headshots/college-football/players/full/4571114.png","alt":"JJ Jenkins"},"jersey":"2","position":{"name":"Wide Receiver","displayName":"Wide Receiver","abbreviation":"WR"},"status":{"id":"2","name":"Inactive","type":"inactive","abbreviation":"Inactive"}},"mainStat":{"value":"44","label":"YDS"},"summary":"2 REC, 1 TD"}]},{"name":"sacks","displayName":"Sacks","leaders":[{"displayValue":"1","value":1.0,"athlete":{"id":"4693848","uid":"s:20~l:23~a:4693848","guid":"df944d0b-0fe0-324f-828e-8c27429f7366","lastName":"Dolac","fullName":"Shaun Dolac","displayName":"Shaun Dolac","shortName":"S. Dolac","links":[{"rel":["playercard","desktop","athlete"],"href":"https://www.espn.com/college-football/player/_/id/4693848/shaun-dolac","text":"Player Card"}],"headshot":{"href":"https://a.espncdn.com/i/headshots/college-football/players/full/4693848.png","alt":"Shaun Dolac"},"jersey":"52","position":{"name":"Linebacker","displayName":"Linebacker","abbreviation":"LB"},"status":{"id":"2","name":"Inactive","type":"inactive","abbreviation":"Inactive"}},"mainStat":{"value":"1","label":"SACKS"},"summary":""}]},{"name":"totalTackles","displayName":"Tackles","leaders":[{"displayValue":"16","value":16.0,"athlete":{"id":"4693848","uid":"s:20~l:23~a:4693848","guid":"df944d0b-0fe0-324f-828e-8c27429f7366","lastName":"Dolac","fullName":"Shaun Dolac","displayName":"Shaun Dolac","shortName":"S. Dolac","links":[{"rel":["playercard","desktop","athlete"],"href":"https://www.espn.com/college-football/player/_/id/4693848/shaun-dolac","text":"Player Card"}],"headshot":{"href":"https://a.espncdn.com/i/headshots/college-football/players/full/4693848.png","alt":"Shaun Dolac"},"jersey":"52","position":{"name":"Linebacker","displayName":"Linebacker","abbreviation":"LB"},"status":{"id":"2","name":"Inactive","type":"inactive","abbreviation":"Inactive"}},"mainStat":{"value":"16","label":"TOT"},"summary":"8 SOLO"}]}]},"113":{"record":[{"type":"total","summary":"0-3","displayValue":"0-3"},{"type":"road","summary":"0-2","displayValue":"0-2"},{"type":"vsconf","summary":"0-0","displayValue":"0-0"}],"linescores":[{"displayValue":"0"},{"displayValue":"3"},{"displayValue":"0"},{"displayValue":"0"}],"statistics":[{"name":"firstDowns","displayValue":"11","value":11.0,"label":"1st Downs"},{"name":"thirdDownEff","displayValue":"4-17","value":0.2352941176,"label":"3rd down efficiency"},{"name":"fourthDownEff","displayValue":"2-2","value":1,"label":"4th down efficiency"},{"name":"totalYards","displayValue":"193","value":"-","label":"Total Yards"},{"name":"netPassingYards","displayValue":"121","value":121.0,"label":"Passing"},{"name":"completionAttempts","displayValue":"14/29","value":"-","label":"Comp/Att"},{"name":"yardsPerPass","displayValue":"4.2","value":4.172,"label":"Yards per pass"},{"name":"rushingYards","displayValue":"72","value":72.0,"label":"Rushing"},{"name":"rushingAttempts","displayValue":"37","value":37.0,"label":"Rushing Attempts"},{"name":"yardsPerRushAttempt","displayValue":"1.9","value":1.946,"label":"Yards per rush"},{"name":"totalPenaltiesYards","displayValue":"6-45","value":"-","label":"Penalties"},{"name":"turnovers","displayValue":"1","value":"-","label":"Turnovers"},{"name":"fumblesLost","displayValue":"0","value":0.0,"label":"Fumbles lost"},{"name":"interceptions","displayValue":"1","value":1.0,"label":"Interceptions thrown"},{"name":"possessionTime","displayValue":"32:04","value":1924,"label":"Possession"}],"leaders":[{"name":"passingYards","displayName":"Passing Yards","leaders":[{"displayValue":"14/29, 121 YDS, 1 INT","value":121.0,"athlete":{"id":"4426430","uid":"s:20~l:23~a:4426430","guid":"93645ea2-22ff-787f-6a43-fe31af4e8f0e","lastName":"Phommachanh","fullName":"Taisun Phommachanh","displayName":"Taisun Phommachanh","shortName":"T. Phommachanh","links":[{"rel":["playercard","desktop","athlete"],"href":"https://www.espn.com/college-football/player/_/id/4426430/taisun-phommachanh","text":"Player Card"}],"headshot":{"href":"https://a.espncdn.com/i/headshots/college-football/players/full/4426430.png","alt":"Taisun Phommachanh"},"jersey":"3","position":{"name":"Quarterback","displayName":"Quarterback","abbreviation":"QB"},"status":{"id":"2","name":"Inactive","type":"inactive","abbreviation":"Inactive"}},"mainStat":{"value":"121","label":"YDS"},"summary":"14/29, 1 INT"}]},{"name":"rushingYards","displayName":"Rushing Yards","leaders":[{"displayValue":"8 CAR, 36 YDS","value":36.0,"athlete":{"id":"4433965","uid":"s:20~l:23~a:4433965","guid":"17670455-3124-3e8d-98b8-3a98d92ee531","lastName":"Campbell","fullName":"Brandon Campbell","displayName":"Brandon Campbell","shortName":"B. Campbell","links":[{"rel":["playercard","desktop","athlete"],"href":"https://www.espn.com/college-football/player/_/id/4433965/brandon-campbell","text":"Player Card"}],"headshot":{"href":"https://a.espncdn.com/i/headshots/college-football/players/full/4433965.png","alt":"Brandon Campbell"},"jersey":"23","position":{"name":"Running Back","displayName":"Running Back","abbreviation":"RB"},"status":{"id":"2","name":"Inactive","type":"inactive","abbreviation":"Inactive"}},"mainStat":{"value":"36","label":"YDS"},"summary":"8 CAR"}]},{"name":"receivingYards","displayName":"Receiving Yards","leaders":[{"displayValue":"4 REC, 58 YDS","value":58.0,"athlete":{"id":"4900879","uid":"s:20~l:23~a:4900879","guid":"09c188ef-97d9-34cd-9e6b-aa69b138bddb","lastName":"Gibson","fullName":"Jacquon Gibson","displayName":"Jacquon Gibson","shortName":"J. Gibson","links":[{"rel":["playercard","desktop","athlete"],"href":"https://www.espn.com/college-football/player/_/id/4900879/jacquon-gibson","text":"Player Card"}],"headshot":{"href":"https://a.espncdn.com/i/headshots/college-football/players/full/4900879.png","alt":"Jacquon Gibson"},"jersey":"2","position":{"name":"Wide Receiver","displayName":"Wide Receiver","abbreviation":"WR"},"status":{"id":"1","name":"Active","type":"active","abbreviation":"Active"}},"mainStat":{"value":"58","label":"YDS"},"summary":"4 REC"}]},{"name":"sacks","displayName":"Sacks","leaders":[{"displayValue":"1","value":1.0,"athlete":{"id":"4705085","uid":"s:20~l:23~a:4705085","guid":"34fbdc9b-ee93-3c1d-af54-c88a019606bf","lastName":"Julien","fullName":"Louce Julien","displayName":"Louce Julien","shortName":"L. Julien","links":[{"rel":["playercard","desktop","athlete"],"href":"https://www.espn.com/college-football/player/_/id/4705085/louce-julien","text":"Player Card"}],"headshot":{"href":"https://a.espncdn.com/i/headshots/college-football/players/full/4705085.png","alt":"Louce Julien"},"jersey":"9","position":{"name":"Defensive End","displayName":"Defensive End","abbreviation":"DE"},"status":{"id":"1","name":"Active","type":"active","abbreviation":"Active"}},"mainStat":{"value":"1","label":"SACKS"},"summary":""}]},{"name":"totalTackles","displayName":"Tackles","leaders":[{"displayValue":"8","value":8.0,"athlete":{"id":"4432308","uid":"s:20~l:23~a:4432308","guid":"dd0717e3-e150-3801-a713-a7250edbdfe2","lastName":"Johnson","fullName":"Gerrell Johnson","displayName":"Gerrell Johnson","shortName":"G. Johnson","links":[{"rel":["playercard","desktop","athlete"],"href":"https://www.espn.com/college-football/player/_/id/4432308/gerrell-johnson","text":"Player Card"}],"headshot":{"href":"https://a.espncdn.com/i/headshots/college-football/players/full/4432308.png","alt":"Gerrell Johnson"},"jersey":"22","position":{"name":"Linebacker","displayName":"Linebacker","abbreviation":"LB"},"status":{"id":"2","name":"Inactive","type":"inactive","abbreviation":"Inactive"}},"mainStat":{"value":"8","label":"TOT"},"summary":"2 SOLO"}]}]},"game_id":401629041,"season":2024,"week":3}